hexseg/__init__.py
hexseg/core.py
hexseg-0.1.3.dist-info/licenses/LICENSE
hexseg-0.1.3.dist-info/METADATA
hexseg-0.1.3.dist-info/WHEEL
hexseg-0.1.3.dist-info/top_level.txt
hexseg-0.1.3.dist-info/RECORD
