Metadata-Version: 2.4
Name: hexseg
Version: 0.1.3
Summary: Spatial crime analysis with hexagons and street segments
Author-email: Iain Agar <routineactivity85@gmail.com>
Requires-Python: >=3.8
License-File: LICENSE
Requires-Dist: pandas
Requires-Dist: numpy
Requires-Dist: geopandas
Requires-Dist: h3
Requires-Dist: shapely
Requires-Dist: scikit-learn
Requires-Dist: networkx
Requires-Dist: folium
Dynamic: license-file
